logs_parser/__init__.py
logs_parser/log_parser.py
LogsParser-0.0.1.dist-info/METADATA
LogsParser-0.0.1.dist-info/WHEEL
LogsParser-0.0.1.dist-info/top_level.txt
LogsParser-0.0.1.dist-info/RECORD
