Metadata-Version: 2.1
Name: LogsParser
Version: 0.0.1
Summary: Classifies senteces as logs or not
Home-page: UNKNOWN
Author: madhav47
Author-email: madhav.vats@codenation.co.in
License: UNKNOWN
Keywords: python,logs,parsing
Platform: UNKNOWN
Classifier: Development Status :: 1 - Planning
Classifier: Intended Audience :: Developers
Classifier: Programming Language :: Python :: 3
Classifier: Operating System :: Unix
Classifier: Operating System :: MacOS :: MacOS X
Classifier: Operating System :: Microsoft :: Windows
Requires-Dist: boto3
Requires-Dist: numpy
Requires-Dist: pandas
Requires-Dist: typing
